LICENSE.txt
MANIFEST.in
README.md
pyproject.toml
src/danoan/journal_manager/__init__.py
src/danoan/journal_manager/assets/templates/file-monitor/file-monitor-action.tpl.sh
src/danoan/journal_manager/assets/templates/file-monitor/file-monitor.tpl.sh
src/danoan/journal_manager/assets/templates/http-server/init.js
src/danoan/journal_manager/assets/templates/http-server/package.json
src/danoan/journal_manager/assets/templates/material-index/index.tpl.html
src/danoan/journal_manager/assets/templates/material-index/assets/images/arrow-down.svg
src/danoan/journal_manager/assets/templates/material-index/assets/images/favicon.png
src/danoan/journal_manager/assets/templates/material-index/assets/javascripts/bundle.078830c0.min.js
src/danoan/journal_manager/assets/templates/material-index/assets/javascripts/bundle.078830c0.min.js.map
src/danoan/journal_manager/assets/templates/material-index/assets/stylesheets/main.20d9efc8.min.css
src/danoan/journal_manager/assets/templates/material-index/assets/stylesheets/main.20d9efc8.min.css.map
src/danoan/journal_manager/assets/templates/material-index/assets/stylesheets/palette.cbb835fc.min.css
src/danoan/journal_manager/assets/templates/material-index/assets/stylesheets/palette.cbb835fc.min.css.map
src/danoan/journal_manager/cli/__init__.py
src/danoan/journal_manager/cli/cli.py
src/danoan/journal_manager/cli/utils.py
src/danoan/journal_manager/cli/commands/__init__.py
src/danoan/journal_manager/cli/commands/build.py
src/danoan/journal_manager/cli/commands/journal.py
src/danoan/journal_manager/cli/commands/setup.py
src/danoan/journal_manager/cli/commands/template.py
src/danoan/journal_manager/cli/commands/journal_commands/__init__.py
src/danoan/journal_manager/cli/commands/journal_commands/activate.py
src/danoan/journal_manager/cli/commands/journal_commands/create.py
src/danoan/journal_manager/cli/commands/journal_commands/deactivate.py
src/danoan/journal_manager/cli/commands/journal_commands/deregister.py
src/journal_manager.egg-info/PKG-INFO
src/journal_manager.egg-info/SOURCES.txt
src/journal_manager.egg-info/dependency_links.txt
src/journal_manager.egg-info/entry_points.txt
src/journal_manager.egg-info/requires.txt
src/journal_manager.egg-info/top_level.txt
