Metadata-Version: 2.4
Name: journal-manager
Version: 1.2
Author-email: Daniel Martins Antunes <danoan2008@gmail.com>
License: MIT License
Project-URL: Documentation, https://github.com/danoan/journal-manager#readme
Project-URL: Issues, https://github.com/danoan/journal-manager/issues
Project-URL: Source, https://github.com/danoan/journal-manager
Classifier: Development Status :: 4 - Beta
Classifier: Programming Language :: Python
Classifier: Programming Language :: Python :: 3.9
Classifier: Programming Language :: Python :: Implementation :: CPython
Classifier: Programming Language :: Python :: Implementation :: PyPy
Requires-Python: >=3.10
License-File: LICENSE.txt
Requires-Dist: dataclasses
Requires-Dist: jinja2
Requires-Dist: toml
Requires-Dist: typing_extensions
Requires-Dist: mkdocs
Requires-Dist: mkdocs-material
Requires-Dist: importlib_resources
Requires-Dist: quick-notes
Requires-Dist: toml_dataclass
Dynamic: license-file
